pyrga/__init__.py
pyrga/driver.py
pyrga-0.0.3.dist-info/LICENSE
pyrga-0.0.3.dist-info/METADATA
pyrga-0.0.3.dist-info/WHEEL
pyrga-0.0.3.dist-info/top_level.txt
pyrga-0.0.3.dist-info/RECORD
