Metadata-Version: 2.1
Name: pyrga
Version: 0.0.3
Summary: Serial interface driver for SRS RGA (residual gas analyzer) mass-spectrometer
Home-page: https://github.com/nagimov/pyrga
Author: Ruslan Nagimov
Author-email: nagimov@outlook.com
License: MIT License
Keywords: RGA,mass spectrometry,vacuum
Platform: UNKNOWN
Classifier: Development Status :: 3 - Alpha
Classifier: Intended Audience :: Science/Research
Classifier: License :: OSI Approved :: MIT License
Classifier: Operating System :: OS Independent
Classifier: Programming Language :: Python
Classifier: Programming Language :: Python :: 3
Classifier: Programming Language :: Python :: 3.4
Classifier: Programming Language :: Python :: 3.5
Classifier: Programming Language :: Python :: 3.6
Classifier: Programming Language :: Python :: 3.7
Classifier: Programming Language :: Python :: 3.8
Classifier: Topic :: Scientific/Engineering
Classifier: Topic :: Scientific/Engineering :: Chemistry
Classifier: Topic :: Scientific/Engineering :: Interface Engine/Protocol Translator
Classifier: Topic :: Scientific/Engineering :: Physics
Requires-Dist: pyserial (>=3.0)
